motionpdf/__init__.py
motionpdf/app.py
motionpdf/motion.py
motionpdf-0.0.1.dist-info/LICENSE
motionpdf-0.0.1.dist-info/METADATA
motionpdf-0.0.1.dist-info/WHEEL
motionpdf-0.0.1.dist-info/entry_points.txt
motionpdf-0.0.1.dist-info/top_level.txt
motionpdf-0.0.1.dist-info/RECORD
