Metadata-Version: 2.1
Name: motionpdf
Version: 0.0.1
Summary: A script built on Tesseract-OCR for converting .pdf to .txt
Home-page: https://github.com/Ahmad-Bamba/MotionPDF
Author: Ahmad Bamba
Author-email: ahmad.eb.bamba@gmail.com
License: MIT License
Keywords: pdf,txt,text,plain text,convert,read,ocr
Platform: UNKNOWN
Classifier: Programming Language :: Python :: 3
Classifier: License :: OSI Approved :: MIT License
Classifier: Operating System :: OS Independent
Requires-Python: >=3.8
License-File: LICENSE
Requires-Dist: pytesseract
Requires-Dist: pdf2image
Requires-Dist: Pillow (>=7.0)
